{"010100":{"mc":"铁路运输服务","zzscezsbj":"N","yyscezsbj":"Y","zzssl":0.0,"yyssl":0.03,"zzs":{"3.0%":0.03,"10.0%":0.1,"11.0%":0.11},"yys":{"3.0%":0.03}},"010201":{"mc":"陆路旅客运输服务","zzscezsbj":"N","yyscezsbj":"Y","zzssl":0.0,"yyssl":0.03,"zzs":{"3.0%":0.03,"10.0%":0.1,"11.0%":0.11},"yys":{"3.0%":0.03}},"010202":{"mc":"陆路货物运输服务","zzscezsbj":"N","yyscezsbj":"Y","zzssl":0.0,"yyssl":0.03,"zzs":{"10.0%":0.1,"11.0%":0.11},"yys":{"3.0%":0.03}},"010300":{"mc":"水路运输服务","zzscezsbj":"N","yyscezsbj":"Y","zzssl":0.0,"yyssl":0.03,"zzs":{"3.0%":0.03,"10.0%":0.1,"11.0%":0.11},"yys":{"3.0%":0.03}},"010400":{"mc":"航空运输服务","zzscezsbj":"N","yyscezsbj":"Y","zzssl":0.0,"yyssl":0.03,"zzs":{"3.0%":0.03,"10.0%":0.1,"11.0%":0.11},"yys":{"3.0%":0.03}},"010500":{"mc":"管道运输服务","zzscezsbj":"N","yyscezsbj":"Y","zzssl":0.0,"yyssl":0.03,"zzs":{"10.0%":0.1,"11.0%":0.11},"yys":{"3.0%":0.03}},"020000":{"mc":"邮政服务","zzscezsbj":"N","yyscezsbj":"N","zzssl":0.0,"yyssl":0.0,"zzs":{"10.0%":0.1,"11.0%":0.11},"yys":{"3.0%":0.03,"5.0%":0.05}},"030100":{"mc":"基础电信服务","zzscezsbj":"N","yyscezsbj":"Y","zzssl":0.0,"yyssl":0.03,"zzs":{"10.0%":0.1,"11.0%":0.11},"yys":{"3.0%":0.03}},"030200":{"mc":"增值电信服务","zzscezsbj":"Y","yyscezsbj":"Y","zzssl":0.06,"yyssl":0.03,"zzs":{"6.0%":0.06},"yys":{"3.0%":0.03}},"040100":{"mc":"工程服务","zzscezsbj":"Y","yyscezsbj":"Y","zzssl":0.0,"yyssl":0.03,"zzs":{"3.0%":0.03,"10.0%":0.1,"11.0%":0.11},"yys":{"3.0%":0.03}},"040200":{"mc":"安装服务","zzscezsbj":"Y","yyscezsbj":"Y","zzssl":0.0,"yyssl":0.03,"zzs":{"3.0%":0.03,"10.0%":0.1,"11.0%":0.11},"yys":{"3.0%":0.03}},"040300":{"mc":"修缮服务","zzscezsbj":"Y","yyscezsbj":"Y","zzssl":0.0,"yyssl":0.03,"zzs":{"3.0%":0.03,"10.0%":0.1,"11.0%":0.11},"yys":{"3.0%":0.03}},"040400":{"mc":"装饰服务","zzscezsbj":"Y","yyscezsbj":"Y","zzssl":0.0,"yyssl":0.03,"zzs":{"3.0%":0.03,"10.0%":0.1,"11.0%":0.11},"yys":{"3.0%":0.03}},"040500":{"mc":"其他建筑服务","zzscezsbj":"Y","yyscezsbj":"Y","zzssl":0.0,"yyssl":0.03,"zzs":{"3.0%":0.03,"10.0%":0.1,"11.0%":0.11},"yys":{"3.0%":0.03}},"050100":{"mc":"贷款服务","zzscezsbj":"Y","yyscezsbj":"Y","zzssl":0.0,"yyssl":0.0,"zzs":{"3.0%":0.03,"6.0%":0.06},"yys":{"3.0%":0.03,"5.0%":0.05}},"050200":{"mc":"直接收费金融服务","zzscezsbj":"N","yyscezsbj":"Y","zzssl":0.0,"yyssl":0.0,"zzs":{"3.0%":0.03,"6.0%":0.06},"yys":{"3.0%":0.03,"5.0%":0.05}},"050300":{"mc":"人身保险服务","zzscezsbj":"N","yyscezsbj":"Y","zzssl":0.06,"yyssl":0.05,"zzs":{"6.0%":0.06},"yys":{"5.0%":0.05}},"050400":{"mc":"财产保险服务","zzscezsbj":"N","yyscezsbj":"Y","zzssl":0.06,"yyssl":0.05,"zzs":{"6.0%":0.06},"yys":{"5.0%":0.05}},"050500":{"mc":"金融商品转让","zzscezsbj":"Y","yyscezsbj":"Y","zzssl":0.0,"yyssl":0.0,"zzs":{"3.0%":0.03,"6.0%":0.06},"yys":{"3.0%":0.03,"5.0%":0.05}},"060101":{"mc":"研发服务","zzscezsbj":"N","yyscezsbj":"N","zzssl":0.06,"yyssl":0.05,"zzs":{"6.0%":0.06},"yys":{"5.0%":0.05}},"060102":{"mc":"合同能源管理服务","zzscezsbj":"N","yyscezsbj":"N","zzssl":0.06,"yyssl":0.05,"zzs":{"6.0%":0.06},"yys":{"5.0%":0.05}},"060103":{"mc":"工程勘察勘探服务","zzscezsbj":"N","yyscezsbj":"Y","zzssl":0.06,"yyssl":0.05,"zzs":{"6.0%":0.06},"yys":{"5.0%":0.05}},"060104":{"mc":"专业技术服务","zzscezsbj":"N","yyscezsbj":"N","zzssl":0.06,"yyssl":0.05,"zzs":{"6.0%":0.06},"yys":{"5.0%":0.05}},"060201":{"mc":"软件服务","zzscezsbj":"N","yyscezsbj":"N","zzssl":0.06,"yyssl":0.05,"zzs":{"6.0%":0.06},"yys":{"5.0%":0.05}},"060202":{"mc":"电路设计及测试服务","zzscezsbj":"N","yyscezsbj":"N","zzssl":0.06,"yyssl":0.05,"zzs":{"6.0%":0.06},"yys":{"5.0%":0.05}},"060203":{"mc":"信息系统服务","zzscezsbj":"N","yyscezsbj":"N","zzssl":0.06,"yyssl":0.05,"zzs":{"6.0%":0.06},"yys":{"5.0%":0.05}},"060204":{"mc":"业务流程管理服务","zzscezsbj":"N","yyscezsbj":"N","zzssl":0.06,"yyssl":0.05,"zzs":{"6.0%":0.06},"yys":{"5.0%":0.05}},"060205":{"mc":"信息系统增值服务","zzscezsbj":"N","yyscezsbj":"N","zzssl":0.06,"yyssl":0.05,"zzs":{"6.0%":0.06},"yys":{"5.0%":0.05}},"060301":{"mc":"设计服务","zzscezsbj":"N","yyscezsbj":"Y","zzssl":0.0,"yyssl":0.05,"zzs":{"3.0%":0.03,"6.0%":0.06},"yys":{"5.0%":0.05}},"060302":{"mc":"知识产权服务","zzscezsbj":"N","yyscezsbj":"N","zzssl":0.06,"yyssl":0.05,"zzs":{"6.0%":0.06},"yys":{"5.0%":0.05}},"060303":{"mc":"广告服务","zzscezsbj":"N","yyscezsbj":"Y","zzssl":0.06,"yyssl":0.05,"zzs":{"6.0%":0.06},"yys":{"5.0%":0.05}},"060304":{"mc":"会议展览服务","zzscezsbj":"N","yyscezsbj":"N","zzssl":0.06,"yyssl":0.0,"zzs":{"6.0%":0.06},"yys":{"3.0%":0.03,"5.0%":0.05}},"060401":{"mc":"航空服务","zzscezsbj":"N","yyscezsbj":"N","zzssl":0.06,"yyssl":0.03,"zzs":{"6.0%":0.06},"yys":{"3.0%":0.03}},"060402":{"mc":"港口码头服务","zzscezsbj":"N","yyscezsbj":"N","zzssl":0.06,"yyssl":0.03,"zzs":{"6.0%":0.06},"yys":{"3.0%":0.03}},"060403":{"mc":"货运客运场站服务","zzscezsbj":"Y","yyscezsbj":"N","zzssl":0.06,"yyssl":0.03,"zzs":{"6.0%":0.06},"yys":{"3.0%":0.03}},"060404":{"mc":"打捞救助服务","zzscezsbj":"N","yyscezsbj":"N","zzssl":0.06,"yyssl":0.03,"zzs":{"6.0%":0.06},"yys":{"3.0%":0.03}},"060405":{"mc":"装卸搬运服务","zzscezsbj":"N","yyscezsbj":"N","zzssl":0.0,"yyssl":0.03,"zzs":{"3.0%":0.03,"6.0%":0.06},"yys":{"3.0%":0.03}},"060406":{"mc":"仓储服务","zzscezsbj":"N","yyscezsbj":"Y","zzssl":0.0,"yyssl":0.05,"zzs":{"3.0%":0.03,"6.0%":0.06},"yys":{"5.0%":0.05}},"060407":{"mc":"收派服务","zzscezsbj":"N","yyscezsbj":"N","zzssl":0.0,"yyssl":0.03,"zzs":{"3.0%":0.03,"6.0%":0.06},"yys":{"3.0%":0.03}},"060501":{"mc":"不动产融资租赁","zzscezsbj":"Y","yyscezsbj":"Y","zzssl":0.0,"yyssl":0.05,"zzs":{"5.0%":0.05,"10.0%":0.1,"11.0%":0.11},"yys":{"5.0%":0.05}},"060502":{"mc":"不动产经营租赁","zzscezsbj":"N","yyscezsbj":"N","zzssl":0.0,"yyssl":0.0,"zzs":{"3.0%":0.03,"5.0%":0.05,"10.0%":0.1,"11.0%":0.11},"yys":{"3.0%":0.03,"5.0%":0.05}},"060503":{"mc":"有形动产融资租赁","zzscezsbj":"Y","yyscezsbj":"Y","zzssl":0.0,"yyssl":0.05,"zzs":{"3.0%":0.03,"16.0%":0.16,"17.0%":0.17},"yys":{"5.0%":0.05}},"060504":{"mc":"有形动产经营租赁","zzscezsbj":"N","yyscezsbj":"N","zzssl":0.0,"yyssl":0.05,"zzs":{"3.0%":0.03,"16.0%":0.16,"17.0%":0.17},"yys":{"5.0%":0.05}},"060601":{"mc":"认证服务","zzscezsbj":"N","yyscezsbj":"N","zzssl":0.06,"yyssl":0.05,"zzs":{"6.0%":0.06},"yys":{"5.0%":0.05}},"060602":{"mc":"鉴证服务","zzscezsbj":"N","yyscezsbj":"N","zzssl":0.06,"yyssl":0.05,"zzs":{"6.0%":0.06},"yys":{"5.0%":0.05}},"060603":{"mc":"咨询服务","zzscezsbj":"N","yyscezsbj":"N","zzssl":0.06,"yyssl":0.05,"zzs":{"6.0%":0.06},"yys":{"5.0%":0.05}},"060701":{"mc":"广播影视节目（作品）制作服务","zzscezsbj":"N","yyscezsbj":"N","zzssl":0.06,"yyssl":0.0,"zzs":{"6.0%":0.06},"yys":{"3.0%":0.03,"5.0%":0.05}},"060702":{"mc":"广播影视节目（作品）发行服务","zzscezsbj":"N","yyscezsbj":"N","zzssl":0.06,"yyssl":0.05,"zzs":{"6.0%":0.06},"yys":{"5.0%":0.05}},"060703":{"mc":"广播影视节目（作品）播映服务","zzscezsbj":"N","yyscezsbj":"N","zzssl":0.0,"yyssl":0.03,"zzs":{"3.0%":0.03,"6.0%":0.06},"yys":{"3.0%":0.03}},"060801":{"mc":"企业管理服务","zzscezsbj":"N","yyscezsbj":"Y","zzssl":0.06,"yyssl":0.05,"zzs":{"6.0%":0.06},"yys":{"5.0%":0.05}},"060802":{"mc":"经纪代理服务","zzscezsbj":"Y","yyscezsbj":"Y","zzssl":0.0,"yyssl":0.05,"zzs":{"5.0%":0.05,"6.0%":0.06},"yys":{"5.0%":0.05}},"060803":{"mc":"人力资源服务","zzscezsbj":"Y","yyscezsbj":"Y","zzssl":0.0,"yyssl":0.05,"zzs":{"5.0%":0.05,"6.0%":0.06},"yys":{"5.0%":0.05}},"060804":{"mc":"安全保护服务","zzscezsbj":"Y","yyscezsbj":"N","zzssl":0.0,"yyssl":0.05,"zzs":{"5.0%":0.05,"6.0%":0.06},"yys":{"5.0%":0.05}},"069900":{"mc":"其他现代服务","zzscezsbj":"N","yyscezsbj":"N","zzssl":0.06,"yyssl":0.05,"zzs":{"6.0%":0.06},"yys":{"5.0%":0.05}},"070101":{"mc":"文化服务","zzscezsbj":"N","yyscezsbj":"Y","zzssl":0.0,"yyssl":0.03,"zzs":{"3.0%":0.03,"6.0%":0.06},"yys":{"3.0%":0.03}},"070102":{"mc":"体育服务","zzscezsbj":"N","yyscezsbj":"Y","zzssl":0.0,"yyssl":0.03,"zzs":{"3.0%":0.03,"6.0%":0.06},"yys":{"3.0%":0.03}},"070201":{"mc":"教育服务","zzscezsbj":"N","yyscezsbj":"Y","zzssl":0.0,"yyssl":0.03,"zzs":{"3.0%":0.03,"6.0%":0.06},"yys":{"3.0%":0.03}},"070202":{"mc":"医疗服务","zzscezsbj":"N","yyscezsbj":"N","zzssl":0.06,"yyssl":0.05,"zzs":{"6.0%":0.06},"yys":{"5.0%":0.05}},"070301":{"mc":"旅游服务","zzscezsbj":"Y","yyscezsbj":"Y","zzssl":0.06,"yyssl":0.05,"zzs":{"6.0%":0.06},"yys":{"5.0%":0.05}},"070302":{"mc":"娱乐服务","zzscezsbj":"N","yyscezsbj":"N","zzssl":0.06,"yyssl":0.0,"zzs":{"6.0%":0.06},"yys":{"5.0%":0.05,"6.0%":0.06,"7.000000000000001%":0.07,"8.0%":0.08,"9.0%":0.09,"10.0%":0.1,"11.0%":0.11,"12.0%":0.12,"13.0%":0.13,"14.000000000000002%":0.14,"15.0%":0.15,"16.0%":0.16,"17.0%":0.17,"18.0%":0.18,"19.0%":0.19,"20.0%":0.2}},"070401":{"mc":"餐饮服务","zzscezsbj":"N","yyscezsbj":"N","zzssl":0.06,"yyssl":0.05,"zzs":{"6.0%":0.06},"yys":{"5.0%":0.05}},"070402":{"mc":"住宿服务","zzscezsbj":"N","yyscezsbj":"N","zzssl":0.06,"yyssl":0.05,"zzs":{"6.0%":0.06},"yys":{"5.0%":0.05}},"070500":{"mc":"居民日常服务","zzscezsbj":"N","yyscezsbj":"N","zzssl":0.06,"yyssl":0.05,"zzs":{"6.0%":0.06},"yys":{"5.0%":0.05}},"079900":{"mc":"其他生活服务","zzscezsbj":"N","yyscezsbj":"N","zzssl":0.06,"yyssl":0.05,"zzs":{"6.0%":0.06},"yys":{"5.0%":0.05}},"080100":{"mc":"专利或非专利技术","zzscezsbj":"N","yyscezsbj":"N","zzssl":0.06,"yyssl":0.05,"zzs":{"6.0%":0.06},"yys":{"5.0%":0.05}},"080200":{"mc":"商标和著作权","zzscezsbj":"N","yyscezsbj":"N","zzssl":0.0,"yyssl":0.0,"zzs":{"3.0%":0.03,"6.0%":0.06},"yys":{"3.0%":0.03,"5.0%":0.05}},"080300":{"mc":"土地使用权","zzscezsbj":"Y","yyscezsbj":"Y","zzssl":0.0,"yyssl":0.05,"zzs":{"5.0%":0.05,"10.0%":0.1,"11.0%":0.11},"yys":{"5.0%":0.05}},"080400":{"mc":"其他自然资源使用权","zzscezsbj":"N","yyscezsbj":"N","zzssl":0.06,"yyssl":0.05,"zzs":{"6.0%":0.06},"yys":{"5.0%":0.05}},"089900":{"mc":"其他权益性无形资产","zzscezsbj":"N","yyscezsbj":"N","zzssl":0.06,"yyssl":0.05,"zzs":{"6.0%":0.06},"yys":{"5.0%":0.05}},"090100":{"mc":"销售不动产建筑物","zzscezsbj":"Y","yyscezsbj":"Y","zzssl":0.0,"yyssl":0.05,"zzs":{"5.0%":0.05,"10.0%":0.1,"11.0%":0.11},"yys":{"5.0%":0.05}},"090200":{"mc":"销售不动产构筑物","zzscezsbj":"Y","yyscezsbj":"Y","zzssl":0.0,"yyssl":0.05,"zzs":{"5.0%":0.05,"10.0%":0.1,"11.0%":0.11},"yys":{"5.0%":0.05}}}